navigator/__init__.py
navigator/_version.py
navigator/conf.py
navigator/connections.py
navigator/decorators.py
navigator/extensions.py
navigator/functions.py
navigator/navigator.py
navigator/py.typed
navigator/resources.py
navigator/responses.py
navigator/routes.py
navigator/types.cpp
navigator/types.cpython-310-x86_64-linux-gnu.so
navigator/types.pyx
navigator/version.py
navigator/actions/__init__.py
navigator/actions/abstract.py
navigator/actions/avochato.py
navigator/actions/hubspot.py
navigator/actions/odoo.py
navigator/actions/py.typed
navigator/actions/rest.py
navigator/actions/ticket.py
navigator/actions/zammad.py
navigator/actions/google/__init__.py
navigator/actions/google/conf.py
navigator/actions/google/maps.py
navigator/actions/google/models.py
navigator/actions/google/libs/__init__.py
navigator/applications/__init__.py
navigator/applications/base.cpp
navigator/applications/base.cpython-310-x86_64-linux-gnu.so
navigator/applications/base.pyi
navigator/applications/base.pyx
navigator/applications/py.typed
navigator/applications/startup.py
navigator/background/__init__.py
navigator/background/py.typed
navigator/background/queue/__init__.py
navigator/background/service/__init__.py
navigator/background/tracker/__init__.py
navigator/background/tracker/memory.py
navigator/background/tracker/models.py
navigator/background/tracker/redis.py
navigator/background/wrappers/__init__.py
navigator/brokers/__init__.py
navigator/brokers/connection.py
navigator/brokers/consumer.py
navigator/brokers/pickle.py
navigator/brokers/producer.py
navigator/brokers/py.typed
navigator/brokers/wrapper.py
navigator/brokers/rabbitmq/__init__.py
navigator/brokers/rabbitmq/connection.py
navigator/brokers/rabbitmq/consumer.py
navigator/brokers/rabbitmq/producer.py
navigator/brokers/redis/__init__.py
navigator/brokers/redis/connection.py
navigator/brokers/redis/consumer.py
navigator/brokers/redis/producer.py
navigator_api-2.14.5.dist-info/METADATA
navigator_api-2.14.5.dist-info/WHEEL
navigator_api-2.14.5.dist-info/entry_points.txt
navigator_api-2.14.5.dist-info/top_level.txt
navigator_api-2.14.5.dist-info/RECORD
navigator_api-2.14.5.dist-info/licenses/LICENSE
