Metadata-Version: 2.4
Name: navigator-api
Version: 2.14.5
Summary: Navigator: a batteries-included Web Framework based on aiohttp
Author-email: "Jesus Lara G." <jesuslarag@gmail.com>
Maintainer-email: "Jesus Lara G." <jesuslarag@gmail.com>
License: BSD-3-Clause
Project-URL: Homepage, https://github.com/phenobarbital/navigator
Project-URL: Documentation, https://navigator-api.readthedocs.io
Project-URL: Repository, https://github.com/phenobarbital/navigator.git
Project-URL: Bug Tracker, https://github.com/phenobarbital/navigator/issues
Project-URL: Changelog, https://github.com/phenobarbital/navigator/blob/main/CHANGELOG.md
Project-URL: Funding, https://paypal.me/phenobarbital
Keywords: framework,asyncio,uvloop,aiohttp,navigator,web,async
Classifier: Development Status :: 4 - Beta
Classifier: Environment :: Web Environment
Classifier: Framework :: AsyncIO
Classifier: Intended Audience :: Developers
Classifier: Intended Audience :: System Administrators
Classifier: Operating System :: OS Independent
Classifier: Programming Language :: Python :: 3
Classifier: Programming Language :: Python :: 3.10
Classifier: Programming Language :: Python :: 3.11
Classifier: Programming Language :: Python :: 3.12
Classifier: Programming Language :: Python :: 3.13
Classifier: Programming Language :: Python :: 3 :: Only
Classifier: Typing :: Typed
Classifier: Topic :: Software Development :: Libraries :: Application Frameworks
Classifier: Topic :: Software Development :: Libraries :: Python Modules
Classifier: Topic :: Software Development :: Build Tools
Classifier: Topic :: Internet :: WWW/HTTP :: HTTP Servers
Classifier: Topic :: Internet :: WWW/HTTP
Classifier: License :: OSI Approved :: BSD License
Requires-Python: >=3.10
License-File: LICENSE
Requires-Dist: Cython>=3.0.11
Requires-Dist: aiohttp[speedups]>=3.10.0
Requires-Dist: PySocks>=1.7.1
Requires-Dist: asn1crypto>=1.4.0
Requires-Dist: jinja2>=3.1.6
Requires-Dist: psycopg2-binary>=2.9.9
Requires-Dist: aiosocks>=0.2.6
Requires-Dist: python-slugify>=8.0.1
Requires-Dist: proxylists>=0.12.4
Requires-Dist: httpx<=0.28.1,>=0.25.0
Requires-Dist: beautifulsoup4>=4.12.3
Requires-Dist: polyline>=2.0.1
Requires-Dist: cartopy>=0.22.0
Requires-Dist: matplotlib>=3.8.3
Requires-Dist: sockjs>=0.11.0
Requires-Dist: aiohttp-sse>=2.2.0
Requires-Dist: asyncdb[boto3,default,uvloop]>=2.8.0
Requires-Dist: pyarrow<21.0.0,>=17.0.0
Requires-Dist: navconfig[default]>=1.7.10
Requires-Dist: alt-aiohttp-cors>=0.7.2
Requires-Dist: brotli>=1.1.0
Requires-Dist: brotlicffi>=1.1.0.0
Requires-Dist: aiofile>=3.9.0
Requires-Dist: psutil>=6.0.0
Requires-Dist: aiormq>=6.8.1
Requires-Dist: Faker>=22.2.0
Requires-Dist: google-cloud-core<=2.4.3,>=2.4.0
Requires-Dist: google-cloud-storage<=3.1.0,>=2.19.0
Requires-Dist: cloudpickle>=3.0.0
Requires-Dist: async-timeout>=4.0.3
Requires-Dist: msgpack>=1.1.0
Requires-Dist: babel<=2.17.0,>=2.9.1
Requires-Dist: watchdog>=6.0.0
Requires-Dist: navigator-session>=0.6.5
Requires-Dist: navigator-auth>=0.15.8
Requires-Dist: python-datamodel>=0.10.17
Provides-Extra: locale
Requires-Dist: Babel<=2.17.0,>=2.9.1; extra == "locale"
Provides-Extra: memcache
Requires-Dist: aiomcache>=0.8.2; extra == "memcache"
Provides-Extra: uvloop
Requires-Dist: uvloop>=0.21.0; extra == "uvloop"
Provides-Extra: gunicorn
Requires-Dist: gunicorn>=23.0.0; extra == "gunicorn"
Provides-Extra: production
Requires-Dist: uvloop>=0.21.0; extra == "production"
Requires-Dist: gunicorn>=23.0.0; extra == "production"
Provides-Extra: dev
Requires-Dist: pytest>=5.4.0; extra == "dev"
Requires-Dist: pytest-asyncio>=0.21.0; extra == "dev"
Requires-Dist: pytest-xdist>=2.5.0; extra == "dev"
Requires-Dist: pytest-assume>=2.4.0; extra == "dev"
Requires-Dist: coverage>=6.0; extra == "dev"
Requires-Dist: mypy>=1.0.0; extra == "dev"
Requires-Dist: black>=23.0.0; extra == "dev"
Requires-Dist: isort>=5.12.0; extra == "dev"
Requires-Dist: pylint>=2.17.0; extra == "dev"
Requires-Dist: pre-commit>=3.0.0; extra == "dev"
Provides-Extra: build
Requires-Dist: setuptools>=67.6.1; extra == "build"
Requires-Dist: Cython==3.0.11; extra == "build"
Requires-Dist: wheel>=0.44.0; extra == "build"
Requires-Dist: build>=0.10.0; extra == "build"
Requires-Dist: python-datamodel>=0.10.17; extra == "build"
Requires-Dist: navconfig>=1.9.2; extra == "build"
Requires-Dist: setuptools_scm[toml]>=6.0; extra == "build"
Provides-Extra: test
Requires-Dist: pytest>=5.4.0; extra == "test"
Requires-Dist: pytest-asyncio>=0.21.0; extra == "test"
Requires-Dist: pytest-xdist>=2.5.0; extra == "test"
Requires-Dist: pytest-assume>=2.4.0; extra == "test"
Requires-Dist: coverage>=6.0; extra == "test"
Requires-Dist: aioresponses>=0.7.4; extra == "test"
Requires-Dist: asynctest>=0.13.0; extra == "test"
Provides-Extra: docs
Requires-Dist: sphinx>=6.0.0; extra == "docs"
Requires-Dist: sphinx-rtd-theme>=1.2.0; extra == "docs"
Requires-Dist: myst-parser>=1.0.0; extra == "docs"
Provides-Extra: all
Requires-Dist: navigator-api[gunicorn,locale,memcache,uvloop]; extra == "all"
Dynamic: license-file
